debase/__init__.py
debase/__main__.py
debase/_version.py
debase/build_db.py
debase/campaign_utils.py
debase/caption_pattern.py
debase/cleanup_sequence.py
debase/enzyme_lineage_extractor.py
debase/lineage_format.py
debase/reaction_info_extractor.py
debase/substrate_scope_extractor.py
debase/wrapper.py
debase-2.1.0.dist-info/licenses/LICENSE
debase-2.1.0.dist-info/METADATA
debase-2.1.0.dist-info/WHEEL
debase-2.1.0.dist-info/entry_points.txt
debase-2.1.0.dist-info/top_level.txt
debase-2.1.0.dist-info/RECORD
