Metadata-Version: 2.4
Name: debase
Version: 2.1.0
Summary: Enzyme lineage analysis and sequence extraction package
Home-page: https://github.com/YuemingLong/DEBase
Author: DEBase Team
Author-email: DEBase Team <ylong@caltech.edu>
License: MIT
Project-URL: Homepage, https://github.com/YuemingLong/DEBase
Project-URL: Documentation, https://github.com/YuemingLong/DEBase#readme
Project-URL: Repository, https://github.com/YuemingLong/DEBase
Project-URL: Issues, https://github.com/YuemingLong/DEBase/issues
Classifier: Development Status :: 4 - Beta
Classifier: Intended Audience :: Science/Research
Classifier: License :: OSI Approved :: MIT License
Classifier: Operating System :: OS Independent
Classifier: Programming Language :: Python :: 3
Classifier: Programming Language :: Python :: 3.8
Classifier: Programming Language :: Python :: 3.9
Classifier: Programming Language :: Python :: 3.10
Classifier: Programming Language :: Python :: 3.11
Classifier: Programming Language :: Python :: 3.12
Classifier: Topic :: Scientific/Engineering :: Bio-Informatics
Classifier: Topic :: Scientific/Engineering :: Chemistry
Requires-Python: >=3.8
License-File: LICENSE
Requires-Dist: pandas>=1.0.0
Requires-Dist: PyMuPDF>=1.18.0
Requires-Dist: numpy>=1.19.0
Requires-Dist: google-generativeai>=0.3.0
Requires-Dist: biopython>=1.78
Requires-Dist: requests>=2.25.0
Requires-Dist: httpx>=0.24.0
Requires-Dist: tqdm>=4.60.0
Requires-Dist: openpyxl>=3.0.0
Requires-Dist: PyPDF2>=2.0.0
Requires-Dist: Pillow>=8.0.0
Requires-Dist: networkx>=2.5
Requires-Dist: json-repair>=0.1.0
Provides-Extra: rdkit
Requires-Dist: rdkit>=2020.03.1; extra == "rdkit"
Provides-Extra: dev
Requires-Dist: pytest>=6.0; extra == "dev"
Requires-Dist: pytest-cov; extra == "dev"
Requires-Dist: black; extra == "dev"
Requires-Dist: isort; extra == "dev"
Requires-Dist: flake8; extra == "dev"
Requires-Dist: mypy; extra == "dev"
Provides-Extra: docs
Requires-Dist: sphinx>=4.0; extra == "docs"
Requires-Dist: sphinx-rtd-theme; extra == "docs"
Requires-Dist: myst-parser; extra == "docs"
Dynamic: author
Dynamic: home-page
Dynamic: license-file
Dynamic: requires-python
